ragstruct/__init__.py
ragstruct/core.py
ragstruct/postinstall.py
ragstruct/setup_prompt.py
ragstruct/structurer.py
ragstruct-0.1.0.dist-info/METADATA
ragstruct-0.1.0.dist-info/WHEEL
ragstruct-0.1.0.dist-info/entry_points.txt
ragstruct-0.1.0.dist-info/top_level.txt
ragstruct-0.1.0.dist-info/RECORD
