Metadata-Version: 2.4
Name: ragstruct
Version: 0.1.0
Summary: ragstruct - A Pseudo-Finetuning RAG Framework for structured JSON-based retrieval
Home-page: https://github.com/Joshikarank/ragstruct
Author: Joshikaran K
Author-email: Joshikaran K <joshikaran2002@gmail.com>
License: MIT
Project-URL: Homepage, https://github.com/Joshikarank/ragstruct
Project-URL: Repository, https://github.com/Joshikarank/ragstruct
Project-URL: Issues, https://github.com/Joshikarank/ragstruct/issues
Requires-Python: >=3.7
Requires-Dist: numpy
Requires-Dist: sentence-transformers
Requires-Dist: scikit-learn
Dynamic: author
Dynamic: home-page
Dynamic: requires-python
